hudu_api_ctek/__init__.py
hudu_api_ctek/assets.py
hudu_api_ctek/companies.py
hudu_api_ctek/magicdash.py
hudu_api_ctek/users.py
hudu_api_ctek-0.0.48.dist-info/LICENSE
hudu_api_ctek-0.0.48.dist-info/METADATA
hudu_api_ctek-0.0.48.dist-info/WHEEL
hudu_api_ctek-0.0.48.dist-info/top_level.txt
hudu_api_ctek-0.0.48.dist-info/RECORD
