Metadata-Version: 2.1
Name: hudu_api_ctek
Version: 0.0.48
Summary: A few functions for the Hudu API
Author-email: Dan S <dan@cybertek.systems>
Classifier: Programming Language :: Python :: 3
Classifier: License :: OSI Approved :: MIT License
Classifier: Operating System :: OS Independent
Requires-Python: >=3.8
License-File: LICENSE
